main.py
feishulogger-0.1.1.dist-info/METADATA
feishulogger-0.1.1.dist-info/WHEEL
feishulogger-0.1.1.dist-info/top_level.txt
feishulogger-0.1.1.dist-info/RECORD
