Metadata-Version: 2.4
Name: feishuLogger
Version: 0.1.1
Summary: A logger for sending logs to Feishu
Requires-Python: >=3.11
Requires-Dist: requests>=2.32.4
Requires-Dist: urllib3>=2.5.0
